asyncwiki/__init__.py
asyncwiki/config.py
asyncwiki/exc.py
asyncwiki/logger.py
asyncwiki/main.py
asyncwiki/params.py
asyncwiki/tuples.py
asyncwiki/types.py
asyncwiki/database/__init__.py
asyncwiki/database/engine.py
asyncwiki/database/orm.py
asyncwiki/database/tables.py
asyncwiki/searchers/__init__.py
asyncwiki/searchers/wikiDBSearcher.py
asyncwiki/searchers/wikiWebSearcher.py
asyncwiki/utils/__init__.py
asyncwiki/utils/wikiSyncDef.py
asyncwiki-0.1.3.dist-info/LICENSE
asyncwiki-0.1.3.dist-info/METADATA
asyncwiki-0.1.3.dist-info/WHEEL
asyncwiki-0.1.3.dist-info/top_level.txt
asyncwiki-0.1.3.dist-info/RECORD
